harvester/__init__.py
harvester/config.py
harvester/csw.py
harvester/data_gov_api.py
harvester/data_json.py
harvester/harvested_source.py
harvester/iso_geo.py
harvester/logs.py
harvester/validator_constants.py
harvester/adapters/__init__.py
harvester/adapters/ckan_dataset_adapters.py
harvester/adapters/ckan_resource_adapters.py
harvester/adapters/datasets/__init__.py
harvester/adapters/datasets/csw.py
harvester/adapters/datasets/data_json.py
harvester/adapters/resources/__init__.py
harvester/adapters/resources/csw.py
harvester/adapters/resources/data_json.py
harvester/settings/__init__.py
harvester/settings/ckan_settings.py
harvester/templates/harvest-report.html
ckan_harvester-0.109.dist-info/METADATA
ckan_harvester-0.109.dist-info/WHEEL
ckan_harvester-0.109.dist-info/top_level.txt
ckan_harvester-0.109.dist-info/RECORD
