Metadata-Version: 2.1
Name: ckan-harvester
Version: 0.109
Summary: Harvester Next Generation Core for CKAN
Home-page: https://gitlab.com/datopian/ckan-ng-harvester-core
Author: Datopian
Author-email: contact@datopian.com
License: MIT
Keywords: harvester,CKAN
Platform: UNKNOWN
Classifier: Programming Language :: Python :: 3
Classifier: License :: OSI Approved :: MIT License
Classifier: Operating System :: OS Independent
Classifier: Intended Audience :: Developers
Requires-Python: >=3.6
Requires-Dist: python-slugify (>=3.0.0)
Requires-Dist: requests (>=2.20.0)
Requires-Dist: OWSLib (>=0.18.0)
Requires-Dist: datapackage (>=1.6.2)
Requires-Dist: jsonschema (>=3.0.2)
Requires-Dist: rfc3987 (>=1.3.8)
Requires-Dist: validate-email (>=1.3)
Requires-Dist: Jinja2 (>=2.10.1)
Requires-Dist: pathlib (>=1.0.1)
Requires-Dist: importlib-resources (>=1.0.2)
Requires-Dist: lxml (>=4.4.1)
